caseinsensitivedefaultdict.py
caseinsensitivedefaultdict-2025.1.21.dist-info/licenses/LICENSE
caseinsensitivedefaultdict-2025.1.21.dist-info/METADATA
caseinsensitivedefaultdict-2025.1.21.dist-info/WHEEL
caseinsensitivedefaultdict-2025.1.21.dist-info/top_level.txt
caseinsensitivedefaultdict-2025.1.21.dist-info/RECORD
