Metadata-Version: 2.4
Name: caseinsensitivedefaultdict
Version: 2025.1.21
Summary: A case-insensitive version of collections.defaultdict
Author-email: Bart Broere <mail@bartbroere.eu>
Maintainer-email: Bart Broere <mail@bartbroere.eu>
License: MIT License
Project-URL: Homepage, https://github.com/bartbroere/caseinsensitivedefaultdict
Project-URL: Documentation, https://github.com/bartbroere/caseinsensitivedefaultdict
Project-URL: Repository, https://github.com/bartbroere/caseinsensitivedefaultdict
Keywords: case,insensitive,defaultdict
Classifier: Programming Language :: Python
Classifier: Programming Language :: Python :: 3.9
Classifier: Programming Language :: Python :: 3.10
Classifier: Programming Language :: Python :: 3.11
Classifier: Programming Language :: Python :: 3.12
Classifier: Programming Language :: Python :: 3.13
Classifier: Programming Language :: Python :: 3.14
Classifier: License :: OSI Approved :: MIT License
Classifier: Topic :: Software Development :: Libraries
Requires-Python: >=3.9
License-File: LICENSE
Requires-Dist: requests<3
Dynamic: license-file
